ingenious/__init__.py
ingenious/api/__init__.py
ingenious/api/routes/__init__.py
ingenious/api/routes/auth.py
ingenious/api/routes/chat.py
ingenious/api/routes/conversation.py
ingenious/api/routes/custom_workflows.py
ingenious/api/routes/custom_workflows_introspection.py
ingenious/api/routes/custom_workflows_schema.py
ingenious/api/routes/diagnostic.py
ingenious/api/routes/events.py
ingenious/api/routes/message_feedback.py
ingenious/api/routes/prompts.py
ingenious/auth/__init__.py
ingenious/auth/jwt.py
ingenious/auth/middleware.py
ingenious/chunk/strategy/langchain_semantic.py
ingenious/cli/__init__.py
ingenious/cli/__main__.py
ingenious/cli/base.py
ingenious/cli/help_commands.py
ingenious/cli/main.py
ingenious/cli/project_commands.py
ingenious/cli/registry.py
ingenious/cli/search_commands.py
ingenious/cli/server_commands.py
ingenious/cli/test_commands.py
ingenious/cli/utilities.py
ingenious/cli/workflow_commands.py
ingenious/cli/commands/__init__.py
ingenious/cli/commands/help.py
ingenious/cli/commands/help_command.py
ingenious/cli/commands/project.py
ingenious/cli/commands/server.py
ingenious/cli/commands/status_command.py
ingenious/cli/commands/validate_command.py
ingenious/cli/commands/version_command.py
ingenious/client/__init__.py
ingenious/client/azure/__init__.py
ingenious/client/azure/azure_client_builder_factory.py
ingenious/client/azure/builder/__init__.py
ingenious/client/azure/builder/base.py
ingenious/client/azure/builder/blob_client.py
ingenious/client/azure/builder/cosmos_client.py
ingenious/client/azure/builder/openai_chat_completions_client.py
ingenious/client/azure/builder/openai_client.py
ingenious/client/azure/builder/openai_client_async.py
ingenious/client/azure/builder/search_client.py
ingenious/client/azure/builder/search_client_async.py
ingenious/client/azure/builder/sql_client.py
ingenious/common/__init__.py
ingenious/common/enums/__init__.py
ingenious/common/enums/authentication_method.py
ingenious/config/__init__.py
ingenious-0.2.8.dist-info/METADATA
ingenious-0.2.8.dist-info/WHEEL
ingenious-0.2.8.dist-info/entry_points.txt
ingenious-0.2.8.dist-info/licenses/LICENSE
ingenious-0.2.8.dist-info/RECORD
