Metadata-Version: 2.4
Name: ingenious
Version: 0.2.8
Summary: An enterprise-grade Python library for quickly setting up APIs to interact with AI Agents
Project-URL: Homepage, https://github.com/Insight-Services-APAC/ingenious
Project-URL: Documentation, https://insight-services-apac.github.io/ingenious/
Project-URL: Repository, https://github.com/Insight-Services-APAC/ingenious
Project-URL: Issues, https://github.com/Insight-Services-APAC/ingenious/issues
Author-email: John Rampono <john.rampono@insight.com>, Kokko Ng <kokko.ng@insight.com>, Elliot Zhu <elliot.zhu@insight.com>
License: MIT
License-File: LICENSE
Keywords: agent,autogen,azure,fastapi
Classifier: Development Status :: 3 - Alpha
Classifier: Intended Audience :: Developers
Classifier: License :: OSI Approved :: MIT License
Classifier: Programming Language :: Python :: 3
Classifier: Programming Language :: Python :: 3.13
Classifier: Topic :: Scientific/Engineering :: Artificial Intelligence
Classifier: Topic :: Software Development :: Libraries :: Python Modules
Requires-Python: >=3.13
Requires-Dist: aiofiles>=24.1.0
Requires-Dist: aiohttp==3.12.15
Requires-Dist: fastapi==0.115.9
Requires-Dist: pydantic-settings>=2.10.1
Requires-Dist: pydantic==2.11.5
Requires-Dist: python-dotenv>=1.0.1
Requires-Dist: rich==13.7.1
Requires-Dist: structlog==25.4.0
Requires-Dist: typer==0.16.0
Requires-Dist: uvicorn>=0.35.0
Provides-Extra: ai
Requires-Dist: ats>=1.0.8; extra == 'ai'
Requires-Dist: autogen-agentchat>=0.5.7; extra == 'ai'
Requires-Dist: autogen-ext>=0.5.7; extra == 'ai'
Requires-Dist: openai>=1.82.0; extra == 'ai'
Requires-Dist: tiktoken>=0.9.0; extra == 'ai'
Provides-Extra: auth
Requires-Dist: bcrypt==4.3.0; extra == 'auth'
Requires-Dist: passlib>=1.7.4; extra == 'auth'
Requires-Dist: python-jose[cryptography]>=3.5.0; extra == 'auth'
Provides-Extra: azure
Requires-Dist: azure-core==1.34.0; extra == 'azure'
Requires-Dist: azure-cosmos>=4.9.0; extra == 'azure'
Requires-Dist: azure-identity>=1.17.1; extra == 'azure'
Requires-Dist: azure-keyvault-secrets>=4.10.0; extra == 'azure'
Requires-Dist: azure-search-documents>=11.5.2; extra == 'azure'
Requires-Dist: azure-storage-blob>=12.25.1; extra == 'azure'
Provides-Extra: azure-full
Requires-Dist: aiosqlite==0.21.0; extra == 'azure-full'
Requires-Dist: ats>=1.0.8; extra == 'azure-full'
Requires-Dist: autogen-agentchat>=0.5.7; extra == 'azure-full'
Requires-Dist: autogen-ext>=0.5.7; extra == 'azure-full'
Requires-Dist: azure-core==1.34.0; extra == 'azure-full'
Requires-Dist: azure-cosmos>=4.9.0; extra == 'azure-full'
Requires-Dist: azure-identity>=1.17.1; extra == 'azure-full'
Requires-Dist: azure-keyvault-secrets>=4.10.0; extra == 'azure-full'
Requires-Dist: azure-search-documents>=11.5.2; extra == 'azure-full'
Requires-Dist: azure-storage-blob>=12.25.1; extra == 'azure-full'
Requires-Dist: bcrypt==4.3.0; extra == 'azure-full'
Requires-Dist: chromadb>=1.0.11; extra == 'azure-full'
Requires-Dist: fastapi-cli==0.0.7; extra == 'azure-full'
Requires-Dist: flask>=3.1.1; extra == 'azure-full'
Requires-Dist: jinja2==3.1.6; extra == 'azure-full'
Requires-Dist: jsonpickle==4.1.1; extra == 'azure-full'
Requires-Dist: markdown>=3.8.2; extra == 'azure-full'
Requires-Dist: openai>=1.82.0; extra == 'azure-full'
Requires-Dist: pandas>=2.3.1; extra == 'azure-full'
Requires-Dist: passlib>=1.7.4; extra == 'azure-full'
Requires-Dist: psutil>=7.0.0; extra == 'azure-full'
Requires-Dist: pyodbc>=5.2.0; extra == 'azure-full'
Requires-Dist: python-jose[cryptography]>=3.5.0; extra == 'azure-full'
Requires-Dist: tiktoken>=0.9.0; extra == 'azure-full'
Provides-Extra: chunk
Requires-Dist: ijson==3.2.3; extra == 'chunk'
Requires-Dist: jsonlines==3.1.0; extra == 'chunk'
Requires-Dist: langchain-experimental==0.3.4; extra == 'chunk'
Requires-Dist: langchain-openai==0.3.0; extra == 'chunk'
Requires-Dist: langchain-text-splitters==0.3.0; extra == 'chunk'
Requires-Dist: regex==2024.11.6; extra == 'chunk'
Requires-Dist: xxhash==3.5.0; extra == 'chunk'
Provides-Extra: core
Requires-Dist: aiosqlite==0.21.0; extra == 'core'
Requires-Dist: fastapi-cli==0.0.7; extra == 'core'
Requires-Dist: jinja2==3.1.6; extra == 'core'
Requires-Dist: jsonpickle==4.1.1; extra == 'core'
Requires-Dist: markdown>=3.8.2; extra == 'core'
Requires-Dist: pandas>=2.3.1; extra == 'core'
Provides-Extra: database
Requires-Dist: psutil>=7.0.0; extra == 'database'
Requires-Dist: pyodbc>=5.2.0; extra == 'database'
Provides-Extra: dataprep
Requires-Dist: backoff==2.2.0; extra == 'dataprep'
Requires-Dist: scrapfly-sdk==0.8.23; extra == 'dataprep'
Provides-Extra: development
Requires-Dist: ipython==9.2.0; extra == 'development'
Provides-Extra: docs
Requires-Dist: mkdocs-git-revision-date-localized-plugin>=1.4.7; extra == 'docs'
Requires-Dist: mkdocs-minify-plugin>=0.8.0; extra == 'docs'
Requires-Dist: mkdocs-nav-weight>=0.2.0; extra == 'docs'
Requires-Dist: mkdocs-redirects>=1.2.2; extra == 'docs'
Requires-Dist: mkdocs-table-reader-plugin>=3.1.0; extra == 'docs'
Provides-Extra: document-advanced
Requires-Dist: pdfminer-six==20250506; extra == 'document-advanced'
Requires-Dist: unstructured[all-docs]==0.17.2; extra == 'document-advanced'
Provides-Extra: document-processing
Requires-Dist: azure-ai-documentintelligence==1.0.2; extra == 'document-processing'
Requires-Dist: pymupdf==1.26.1; extra == 'document-processing'
Provides-Extra: full
Requires-Dist: aiosqlite==0.21.0; extra == 'full'
Requires-Dist: ats>=1.0.8; extra == 'full'
Requires-Dist: autogen-agentchat>=0.5.7; extra == 'full'
Requires-Dist: autogen-ext>=0.5.7; extra == 'full'
Requires-Dist: azure-ai-documentintelligence==1.0.2; extra == 'full'
Requires-Dist: azure-core==1.34.0; extra == 'full'
Requires-Dist: azure-cosmos>=4.9.0; extra == 'full'
Requires-Dist: azure-identity>=1.17.1; extra == 'full'
Requires-Dist: azure-keyvault-secrets>=4.10.0; extra == 'full'
Requires-Dist: azure-search-documents>=11.5.2; extra == 'full'
Requires-Dist: azure-storage-blob>=12.25.1; extra == 'full'
Requires-Dist: backoff==2.2.0; extra == 'full'
Requires-Dist: bcrypt==4.3.0; extra == 'full'
Requires-Dist: chromadb>=1.0.11; extra == 'full'
Requires-Dist: fastapi-cli==0.0.7; extra == 'full'
Requires-Dist: flask>=3.1.1; extra == 'full'
Requires-Dist: jinja2==3.1.6; extra == 'full'
Requires-Dist: jsonpickle==4.1.1; extra == 'full'
Requires-Dist: markdown>=3.8.2; extra == 'full'
Requires-Dist: matplotlib==3.10.3; extra == 'full'
Requires-Dist: openai>=1.82.0; extra == 'full'
Requires-Dist: pandas>=2.3.1; extra == 'full'
Requires-Dist: passlib>=1.7.4; extra == 'full'
Requires-Dist: psutil>=7.0.0; extra == 'full'
Requires-Dist: pymupdf==1.26.1; extra == 'full'
Requires-Dist: pyodbc>=5.2.0; extra == 'full'
Requires-Dist: python-jose[cryptography]>=3.5.0; extra == 'full'
Requires-Dist: scrapfly-sdk==0.8.23; extra == 'full'
Requires-Dist: seaborn==0.13.2; extra == 'full'
Requires-Dist: sentence-transformers==5.0.0; extra == 'full'
Requires-Dist: tiktoken>=0.9.0; extra == 'full'
Provides-Extra: knowledge-base
Requires-Dist: chromadb>=1.0.11; extra == 'knowledge-base'
Provides-Extra: knowledge-focused
Requires-Dist: aiosqlite==0.21.0; extra == 'knowledge-focused'
Requires-Dist: ats>=1.0.8; extra == 'knowledge-focused'
Requires-Dist: autogen-agentchat>=0.5.7; extra == 'knowledge-focused'
Requires-Dist: autogen-ext>=0.5.7; extra == 'knowledge-focused'
Requires-Dist: chromadb>=1.0.11; extra == 'knowledge-focused'
Requires-Dist: fastapi-cli==0.0.7; extra == 'knowledge-focused'
Requires-Dist: jinja2==3.1.6; extra == 'knowledge-focused'
Requires-Dist: jsonpickle==4.1.1; extra == 'knowledge-focused'
Requires-Dist: markdown>=3.8.2; extra == 'knowledge-focused'
Requires-Dist: openai>=1.82.0; extra == 'knowledge-focused'
Requires-Dist: pandas>=2.3.1; extra == 'knowledge-focused'
Requires-Dist: sentence-transformers==5.0.0; extra == 'knowledge-focused'
Requires-Dist: tiktoken>=0.9.0; extra == 'knowledge-focused'
Provides-Extra: minimal
Provides-Extra: ml
Requires-Dist: sentence-transformers==5.0.0; extra == 'ml'
Provides-Extra: standard
Requires-Dist: aiosqlite==0.21.0; extra == 'standard'
Requires-Dist: ats>=1.0.8; extra == 'standard'
Requires-Dist: autogen-agentchat>=0.5.7; extra == 'standard'
Requires-Dist: autogen-ext>=0.5.7; extra == 'standard'
Requires-Dist: bcrypt==4.3.0; extra == 'standard'
Requires-Dist: fastapi-cli==0.0.7; extra == 'standard'
Requires-Dist: jinja2==3.1.6; extra == 'standard'
Requires-Dist: jsonpickle==4.1.1; extra == 'standard'
Requires-Dist: markdown>=3.8.2; extra == 'standard'
Requires-Dist: openai>=1.82.0; extra == 'standard'
Requires-Dist: pandas>=2.3.1; extra == 'standard'
Requires-Dist: passlib>=1.7.4; extra == 'standard'
Requires-Dist: psutil>=7.0.0; extra == 'standard'
Requires-Dist: pyodbc>=5.2.0; extra == 'standard'
Requires-Dist: python-jose[cryptography]>=3.5.0; extra == 'standard'
Requires-Dist: tiktoken>=0.9.0; extra == 'standard'
Provides-Extra: test
Requires-Dist: httpx==0.28.1; extra == 'test'
Requires-Dist: hypothesis==6.136.2; extra == 'test'
Requires-Dist: mypy==1.16.1; extra == 'test'
Requires-Dist: pip-audit==2.9.0; extra == 'test'
Requires-Dist: pre-commit==4.2.0; extra == 'test'
Requires-Dist: pytest-asyncio==0.26.0; extra == 'test'
Requires-Dist: pytest-cov==6.1.1; extra == 'test'
Requires-Dist: pytest-mock==3.14.0; extra == 'test'
Requires-Dist: pytest-timeout==2.4.0; extra == 'test'
Requires-Dist: pytest==8.3.5; extra == 'test'
Requires-Dist: reportlab==4.4.2; extra == 'test'
Requires-Dist: ruff==0.11.10; extra == 'test'
Requires-Dist: twine==6.0.0; extra == 'test'
Requires-Dist: types-markdown==3.8.0.20250708; extra == 'test'
Requires-Dist: types-psutil==7.0.0.20250601; extra == 'test'
Requires-Dist: types-requests==2.32.4.20250611; extra == 'test'
Requires-Dist: vulture==2.14; extra == 'test'
Provides-Extra: ui
Requires-Dist: flask>=3.1.1; extra == 'ui'
Provides-Extra: visualization
Requires-Dist: matplotlib==3.10.3; extra == 'visualization'
Requires-Dist: seaborn==0.13.2; extra == 'visualization'
